nsq/__init__.py
nsq/backoff.py
nsq/checker.py
nsq/client.py
nsq/connection.py
nsq/constants.py
nsq/exceptions.py
nsq/gevent.py
nsq/reader.py
nsq/response.py
nsq/stats.py
nsq/util.py
nsq/http/__init__.py
nsq/http/nsqd.py
nsq/http/nsqlookupd.py
nsq/sockets/__init__.py
nsq/sockets/base.py
nsq/sockets/deflate.py
nsq/sockets/snappy.py
nsq/sockets/tls.py
nsq_py-0.1.12.data/scripts/nsqlookupd-statsd
nsq_py-0.1.12.dist-info/LICENSE
nsq_py-0.1.12.dist-info/METADATA
nsq_py-0.1.12.dist-info/WHEEL
nsq_py-0.1.12.dist-info/top_level.txt
nsq_py-0.1.12.dist-info/RECORD
