Metadata-Version: 2.1
Name: nsq-py
Version: 0.1.12
Summary: NSQ for Python With Pure Sockets
Home-page: http://github.com/dlecocq/nsq-py
Author: Dan Lecocq
Author-email: dan@moz.com
License: MIT License
Keywords: nsq,queue
Platform: UNKNOWN
Classifier: License :: OSI Approved :: MIT License
Classifier: Programming Language :: Python
Classifier: Intended Audience :: Developers
Classifier: Operating System :: OS Independent
Requires-Dist: requests
Requires-Dist: decorator
Requires-Dist: six
Requires-Dist: statsd
